[{
	"RequestID":"30243450",
	"Description":"Устранение последствий протечек",
	"Type": "3",
	"BeginDate": "/Date(1616515568000)/",
	"Status": "3"
},{
	"RequestID":"30243345",
	"Description":"Уборка помещений",
	"Type": "1",
	"BeginDate": "/Date(1616515568000)/",
	"Status": "1"
},{
	"RequestID":"30242345",
	"Description":"Замена лампочек",
	"Type": "3",
	"BeginDate": "/Date(1616515568000)/",
	"Status": "1"
},{
	"RequestID":"30267885",
	"Description":"Починить дверь в переговорную",
	"Type": "1",
	"BeginDate": "/Date(1616515568000)/",
	"Status": "3"
},{
	"RequestID":"30243356",
	"Description":"Перестановка мебели",
	"Type": "3",
	"BeginDate": "/Date(1616515568000)/",
	"Status": "2"
},{
	"RequestID":"30243343",
	"Description":"Неполадки с разеткой",
	"Type": "1",
	"BeginDate": "/Date(1616515568000)/",
	"Status": "3"
}]
