[{
	"RequestID":"30243450",
	"Description":"Устранение последствий протечек",
	"Type": "REPE",
	"BeginDate": "/Date(1616515568000)/",
	"Status": 3
},{
	"RequestID":"30243345",
	"Description":"Уборка помещений",
	"Type": "PRIO",
	"BeginDate": "/Date(1616515568000)/",
	"Status": 1
},{
	"RequestID":"30242345",
	"Description":"Замена лампочек",
	"Type": "OWN",
	"BeginDate": "/Date(1616515568000)/",
	"Status": 1
},{
	"RequestID":"30267885",
	"Description":"Починить дверь в переговорную",
	"Type": "NEW",
	"BeginDate": "/Date(1616515568000)/",
	"Status": 3
},{
	"RequestID":"30243356",
	"Description":"Перестановка мебели",
	"Type": "INPR",
	"BeginDate": "/Date(1616515568000)/",
	"Status": 2
},{
	"RequestID":"30243343",
	"Description":"Неполадки с разеткой",
	"Type": "NEW",
	"BeginDate": "/Date(1616515568000)/",
	"Status": 3
}]
